{
  "epm-reviews": {
    "2024-02-09": {
      "github-avg-time-to-review": 32.0,
      "github-pr-created": 6,
      "github-repositories": 15,
      "github-reviews": 22,
      "phab-authored": 0,
      "phab-reviewed": 2
    },
    "2024-02-16": {
      "github-avg-time-to-review": 70.2,
      "github-pr-created": 2,
      "github-repositories": 15,
      "github-reviews": 25,
      "phab-authored": 0,
      "phab-reviewed": 2
    },
    "2024-02-23": {
      "github-avg-time-to-review": 25.5,
      "github-pr-created": 4,
      "github-repositories": 15,
      "github-reviews": 16,
      "phab-authored": 0,
      "phab-reviewed": 1
    },
    "2024-03-01": {
      "github-avg-time-to-review": 87.2,
      "github-pr-created": 3,
      "github-repositories": 15,
      "github-reviews": 21,
      "phab-authored": 0,
      "phab-reviewed": 3
    },
    "2024-03-08": {
      "github-avg-time-to-review": 45.3,
      "github-pr-created": 3,
      "github-repositories": 14,
      "github-reviews": 17,
      "phab-authored": 0,
      "phab-reviewed": 2
    },
    "2024-03-15": {
      "github-avg-time-to-review": 132.4,
      "github-pr-created": 3,
      "github-repositories": 12,
      "github-reviews": 25,
      "phab-authored": 0,
      "phab-reviewed": 1
    },
    "2024-03-22": {
      "github-avg-time-to-review": 35.7,
      "github-pr-created": 7,
      "github-repositories": 15,
      "github-reviews": 29,
      "phab-authored": 0,
      "phab-reviewed": 3
    },
    "2024-03-29": {
      "github-avg-time-to-review": 24.0,
      "github-pr-created": 1,
      "github-repositories": 12,
      "github-reviews": 21,
      "phab-authored": 0,
      "phab-reviewed": 3
    },
    "2024-04-05": {
      "github-avg-time-to-review": 33.8,
      "github-pr-created": 6,
      "github-repositories": 10,
      "github-reviews": 15,
      "phab-authored": 0,
      "phab-reviewed": 2
    },
    "2024-04-12": {
      "github-avg-time-to-review": 24.8,
      "github-pr-created": 6,
      "github-repositories": 12,
      "github-reviews": 35,
      "phab-authored": 0,
      "phab-reviewed": 3
    },
    "2024-04-19": {
      "github-avg-time-to-review": 46.0,
      "github-pr-created": 1,
      "github-repositories": 14,
      "github-reviews": 18,
      "phab-authored": 0,
      "phab-reviewed": 2
    },
    "2024-04-26": {
      "github-avg-time-to-review": 36.9,
      "github-pr-created": 3,
      "github-repositories": 13,
      "github-reviews": 31,
      "phab-authored": 0,
      "phab-reviewed": 1
    },
    "2024-05-03": {
      "github-avg-time-to-review": 48.9,
      "github-pr-created": 2,
      "github-repositories": 16,
      "github-reviews": 23,
      "phab-authored": 0,
      "phab-reviewed": 3
    },
    "2024-05-10": {
      "github-avg-time-to-review": 56.1,
      "github-pr-created": 11,
      "github-repositories": 15,
      "github-reviews": 23,
      "phab-authored": 2,
      "phab-reviewed": 3
    },
    "2024-05-17": {
      "github-avg-time-to-review": 51.6,
      "github-pr-created": 1,
      "github-repositories": 14,
      "github-reviews": 20,
      "phab-authored": 0,
      "phab-reviewed": 1
    },
    "2024-05-24": {
      "github-avg-time-to-review": 35.3,
      "github-pr-created": 0,
      "github-repositories": 11,
      "github-reviews": 26,
      "phab-authored": 0,
      "phab-reviewed": 2
    },
    "2024-05-31": {
      "github-avg-time-to-review": 22.8,
      "github-pr-created": 3,
      "github-repositories": 14,
      "github-reviews": 21,
      "phab-authored": 1,
      "phab-reviewed": 4
    },
    "2024-06-07": {
      "github-avg-time-to-review": 19.3,
      "github-pr-created": 8,
      "github-repositories": 16,
      "github-reviews": 32,
      "phab-authored": 1,
      "phab-reviewed": 5
    },
    "2024-06-14": {
      "github-avg-time-to-review": 74.1,
      "github-pr-created": 3,
      "github-repositories": 10,
      "github-reviews": 17,
      "phab-authored": 1,
      "phab-reviewed": 2
    },
    "2024-06-21": {
      "github-avg-time-to-review": 21.2,
      "github-pr-created": 2,
      "github-repositories": 13,
      "github-reviews": 18,
      "phab-authored": 1,
      "phab-reviewed": 0
    },
    "2024-06-28": {
      "github-avg-time-to-review": 34.5,
      "github-pr-created": 3,
      "github-repositories": 11,
      "github-reviews": 17,
      "phab-authored": 0,
      "phab-reviewed": 1
    },
    "2024-07-05": {
      "github-avg-time-to-review": 14.9,
      "github-pr-created": 7,
      "github-repositories": 15,
      "github-reviews": 19,
      "phab-authored": 0,
      "phab-reviewed": 13
    },
    "2024-07-12": {
      "github-avg-time-to-review": 34.8,
      "github-pr-created": 1,
      "github-repositories": 12,
      "github-reviews": 20,
      "phab-authored": 0,
      "phab-reviewed": 1
    },
    "2024-07-19": {
      "github-avg-time-to-review": 17.6,
      "github-pr-created": 1,
      "github-repositories": 9,
      "github-reviews": 16,
      "phab-authored": 0,
      "phab-reviewed": 3
    },
    "2024-07-26": {
      "github-avg-time-to-review": 66.8,
      "github-pr-created": 5,
      "github-repositories": 14,
      "github-reviews": 27,
      "phab-authored": 1,
      "phab-reviewed": 1
    },
    "2024-08-02": {
      "github-avg-time-to-review": 42.1,
      "github-pr-created": 1,
      "github-repositories": 12,
      "github-reviews": 19,
      "phab-authored": 0,
      "phab-reviewed": 3
    },
    "2024-08-09": {
      "github-avg-time-to-review": 60.0,
      "github-pr-created": 4,
      "github-repositories": 16,
      "github-reviews": 25,
      "phab-authored": 3,
      "phab-reviewed": 2
    },
    "2024-08-16": {
      "github-avg-time-to-review": 21.7,
      "github-pr-created": 2,
      "github-repositories": 8,
      "github-reviews": 7,
      "phab-authored": 0,
      "phab-reviewed": 1
    },
    "2024-08-23": {
      "github-avg-time-to-review": 58.8,
      "github-pr-created": 0,
      "github-repositories": 12,
      "github-reviews": 10,
      "phab-authored": 0,
      "phab-reviewed": 3
    },
    "2024-08-30": {
      "github-avg-time-to-review": 25.5,
      "github-pr-created": 7,
      "github-repositories": 17,
      "github-reviews": 30,
      "phab-authored": 0,
      "phab-reviewed": 4
    },
    "2024-09-06": {
      "github-avg-time-to-review": 65.3,
      "github-pr-created": 6,
      "github-repositories": 14,
      "github-reviews": 25,
      "phab-authored": 2,
      "phab-reviewed": 0
    },
    "2024-09-13": {
      "github-avg-time-to-review": 64.7,
      "github-pr-created": 12,
      "github-repositories": 18,
      "github-reviews": 28,
      "phab-authored": 3,
      "phab-reviewed": 1
    },
    "2024-09-20": {
      "github-avg-time-to-review": 29.1,
      "github-pr-created": 8,
      "github-repositories": 17,
      "github-reviews": 36,
      "phab-authored": 1,
      "phab-reviewed": 1
    },
    "2024-09-27": {
      "github-avg-time-to-review": 28.2,
      "github-pr-created": 20,
      "github-repositories": 17,
      "github-reviews": 39,
      "phab-authored": 1,
      "phab-reviewed": 3
    },
    "2024-10-04": {
      "github-avg-time-to-review": 16.1,
      "github-pr-created": 11,
      "github-repositories": 15,
      "github-reviews": 34,
      "phab-authored": 0,
      "phab-reviewed": 3
    },
    "2024-10-11": {
      "github-avg-time-to-review": 24.5,
      "github-pr-created": 7,
      "github-repositories": 12,
      "github-reviews": 19,
      "phab-authored": 0,
      "phab-reviewed": 1
    },
    "2024-10-18": {
      "github-avg-time-to-review": 62.4,
      "github-pr-created": 5,
      "github-repositories": 16,
      "github-reviews": 23,
      "phab-authored": 0,
      "phab-reviewed": 3
    },
    "2024-10-25": {
      "github-avg-time-to-review": 29.0,
      "github-pr-created": 7,
      "github-repositories": 18,
      "github-reviews": 28,
      "phab-authored": 0,
      "phab-reviewed": 2
    },
    "2024-11-01": {
      "github-avg-time-to-review": 24.5,
      "github-pr-created": 4,
      "github-repositories": 15,
      "github-reviews": 21,
      "phab-authored": 0,
      "phab-reviewed": 2
    },
    "2024-11-08": {
      "github-avg-time-to-review": 81.6,
      "github-pr-created": 6,
      "github-repositories": 12,
      "github-reviews": 14,
      "phab-authored": 1,
      "phab-reviewed": 3
    },
    "2024-11-15": {
      "github-avg-time-to-review": 41.6,
      "github-pr-created": 6,
      "github-repositories": 16,
      "github-reviews": 18,
      "phab-authored": 0,
      "phab-reviewed": 1
    },
    "2024-11-22": {
      "github-avg-time-to-review": 51.0,
      "github-pr-created": 4,
      "github-repositories": 15,
      "github-reviews": 25,
      "phab-authored": 1,
      "phab-reviewed": 3
    },
    "2024-11-29": {
      "github-avg-time-to-review": 61.5,
      "github-pr-created": 4,
      "github-repositories": 15,
      "github-reviews": 22,
      "phab-authored": 0,
      "phab-reviewed": 7
    },
    "2024-12-06": {
      "github-avg-time-to-review": 68.8,
      "github-pr-created": 2,
      "github-repositories": 14,
      "github-reviews": 23,
      "phab-authored": 0,
      "phab-reviewed": 2
    },
    "2024-12-13": {
      "github-avg-time-to-review": 24.4,
      "github-pr-created": 6,
      "github-repositories": 13,
      "github-reviews": 25,
      "phab-authored": 0,
      "phab-reviewed": 3
    },
    "2024-12-20": {
      "github-avg-time-to-review": 24.3,
      "github-pr-created": 5,
      "github-repositories": 17,
      "github-reviews": 31,
      "phab-authored": 0,
      "phab-reviewed": 2
    },
    "2024-12-27": {
      "github-avg-time-to-review": 57.1,
      "github-pr-created": 1,
      "github-repositories": 10,
      "github-reviews": 10,
      "phab-authored": 0,
      "phab-reviewed": 2
    },
    "2025-01-03": {
      "github-avg-time-to-review": 94.2,
      "github-pr-created": 5,
      "github-repositories": 12,
      "github-reviews": 11,
      "phab-authored": 2,
      "phab-reviewed": 0
    },
    "2025-01-10": {
      "github-avg-time-to-review": 60.1,
      "github-pr-created": 11,
      "github-repositories": 13,
      "github-reviews": 21,
      "phab-authored": 0,
      "phab-reviewed": 1
    },
    "2025-01-17": {
      "github-avg-time-to-review": 49.3,
      "github-pr-created": 9,
      "github-repositories": 13,
      "github-reviews": 29,
      "phab-authored": 1,
      "phab-reviewed": 0
    },
    "2025-01-24": {
      "github-avg-time-to-review": 122.2,
      "github-pr-created": 5,
      "github-repositories": 14,
      "github-reviews": 16,
      "phab-authored": 1,
      "phab-reviewed": 1
    },
    "2025-01-31": {
      "github-avg-time-to-review": 32.2,
      "github-pr-created": 4,
      "github-repositories": 16,
      "github-reviews": 34,
      "phab-authored": 2,
      "phab-reviewed": 6
    },
    "2025-02-07": {
      "github-avg-time-to-review": 23.1,
      "github-pr-created": 7,
      "github-repositories": 11,
      "github-reviews": 21,
      "phab-authored": 2,
      "phab-reviewed": 3
    },
    "2025-02-14": {
      "github-avg-time-to-review": 67.4,
      "github-pr-created": 8,
      "github-repositories": 14,
      "github-reviews": 20,
      "phab-authored": 3,
      "phab-reviewed": 4
    },
    "2025-02-21": {
      "github-avg-time-to-review": 47.1,
      "github-pr-created": 4,
      "github-repositories": 16,
      "github-reviews": 17,
      "phab-authored": 0,
      "phab-reviewed": 4
    },
    "2025-02-28": {
      "github-avg-time-to-review": 17.9,
      "github-pr-created": 20,
      "github-repositories": 14,
      "github-reviews": 27,
      "phab-authored": 0,
      "phab-reviewed": 5
    },
    "2025-03-07": {
      "github-avg-time-to-review": 27.7,
      "github-pr-created": 17,
      "github-repositories": 21,
      "github-reviews": 32,
      "phab-authored": 0,
      "phab-reviewed": 1
    }
  },
  "jira-issues": {
    "2024-02-09": {
      "backlog": 2,
      "blocked": 1,
      "closed": 6,
      "created": 6,
      "in-progress": 7
    },
    "2024-02-16": {
      "backlog": 2,
      "blocked": 1,
      "closed": 5,
      "created": 5,
      "in-progress": 4
    },
    "2024-02-23": {
      "backlog": 0,
      "blocked": 1,
      "closed": 4,
      "created": 4,
      "in-progress": 2
    },
    "2024-03-01": {
      "backlog": 0,
      "blocked": 1,
      "closed": 2,
      "created": 2,
      "in-progress": 3
    },
    "2024-03-08": {
      "backlog": 1,
      "blocked": 1,
      "closed": 1,
      "created": 1,
      "in-progress": 2
    },
    "2024-03-15": {
      "backlog": 2,
      "blocked": 1,
      "closed": 4,
      "created": 4,
      "in-progress": 4
    },
    "2024-03-22": {
      "backlog": 3,
      "blocked": 0,
      "closed": 10,
      "created": 10,
      "in-progress": 7
    },
    "2024-03-29": {
      "backlog": 1,
      "blocked": 0,
      "closed": 9,
      "created": 9,
      "in-progress": 11
    },
    "2024-04-05": {
      "backlog": 1,
      "blocked": 0,
      "closed": 2,
      "created": 2,
      "in-progress": 9
    },
    "2024-04-12": {
      "backlog": 0,
      "blocked": 0,
      "closed": 4,
      "created": 4,
      "in-progress": 9
    },
    "2024-04-19": {
      "backlog": 0,
      "blocked": 0,
      "closed": 3,
      "created": 3,
      "in-progress": 7
    },
    "2024-04-26": {
      "backlog": 0,
      "blocked": 0,
      "closed": 1,
      "created": 1,
      "in-progress": 5
    },
    "2024-05-03": {
      "backlog": 1,
      "blocked": 0,
      "closed": 3,
      "created": 3,
      "in-progress": 3
    },
    "2024-05-10": {
      "backlog": 0,
      "blocked": 0,
      "closed": 3,
      "created": 3,
      "in-progress": 4
    },
    "2024-05-17": {
      "backlog": 0,
      "blocked": 0,
      "closed": 3,
      "created": 3,
      "in-progress": 2
    },
    "2024-05-24": {
      "backlog": 1,
      "blocked": 0,
      "closed": 7,
      "created": 7,
      "in-progress": 4
    },
    "2024-05-31": {
      "backlog": 2,
      "blocked": 0,
      "closed": 3,
      "created": 3,
      "in-progress": 3
    },
    "2024-06-07": {
      "backlog": 0,
      "blocked": 1,
      "closed": 2,
      "created": 2,
      "in-progress": 3
    },
    "2024-06-14": {
      "backlog": 1,
      "blocked": 1,
      "closed": 3,
      "created": 3,
      "in-progress": 3
    },
    "2024-06-21": {
      "backlog": 1,
      "blocked": 1,
      "closed": 3,
      "created": 3,
      "in-progress": 5
    },
    "2024-06-28": {
      "backlog": 2,
      "blocked": 1,
      "closed": 5,
      "created": 5,
      "in-progress": 1
    },
    "2024-07-05": {
      "backlog": 0,
      "blocked": 1,
      "closed": 3,
      "created": 3,
      "in-progress": 4
    },
    "2024-07-12": {
      "backlog": 0,
      "blocked": 1,
      "closed": 2,
      "created": 2,
      "in-progress": 4
    },
    "2024-07-19": {
      "backlog": 2,
      "blocked": 1,
      "closed": 6,
      "created": 6,
      "in-progress": 1
    },
    "2024-07-26": {
      "backlog": 0,
      "blocked": 1,
      "closed": 5,
      "created": 5,
      "in-progress": 7
    },
    "2024-08-02": {
      "backlog": 1,
      "blocked": 1,
      "closed": 5,
      "created": 5,
      "in-progress": 4
    },
    "2024-08-09": {
      "backlog": 0,
      "blocked": 1,
      "closed": 3,
      "created": 3,
      "in-progress": 6
    },
    "2024-08-16": {
      "backlog": 0,
      "blocked": 1,
      "closed": 0,
      "created": 0,
      "in-progress": 4
    },
    "2024-08-23": {
      "backlog": 0,
      "blocked": 1,
      "closed": 1,
      "created": 1,
      "in-progress": 5
    },
    "2024-08-30": {
      "backlog": 2,
      "blocked": 1,
      "closed": 6,
      "created": 6,
      "in-progress": 7
    },
    "2024-09-06": {
      "backlog": 1,
      "blocked": 0,
      "closed": 3,
      "created": 3,
      "in-progress": 3
    },
    "2024-09-13": {
      "backlog": 2,
      "blocked": 0,
      "closed": 5,
      "created": 5,
      "in-progress": 4
    },
    "2024-09-20": {
      "backlog": 1,
      "blocked": 0,
      "closed": 7,
      "created": 7,
      "in-progress": 5
    },
    "2024-09-27": {
      "backlog": 1,
      "blocked": 0,
      "closed": 4,
      "created": 4,
      "in-progress": 5
    },
    "2024-10-04": {
      "backlog": 3,
      "blocked": 0,
      "closed": 5,
      "created": 5,
      "in-progress": 5
    },
    "2024-10-11": {
      "backlog": 1,
      "blocked": 0,
      "closed": 2,
      "created": 2,
      "in-progress": 5
    },
    "2024-10-18": {
      "backlog": 2,
      "blocked": 0,
      "closed": 9,
      "created": 9,
      "in-progress": 6
    },
    "2024-10-25": {
      "backlog": 1,
      "blocked": 0,
      "closed": 8,
      "created": 8,
      "in-progress": 8
    },
    "2024-11-01": {
      "backlog": 2,
      "blocked": 0,
      "closed": 6,
      "created": 6,
      "in-progress": 8
    },
    "2024-11-08": {
      "backlog": 0,
      "blocked": 0,
      "closed": 5,
      "created": 5,
      "in-progress": 10
    },
    "2024-11-15": {
      "backlog": 1,
      "blocked": 0,
      "closed": 2,
      "created": 2,
      "in-progress": 7
    },
    "2024-11-22": {
      "backlog": 0,
      "blocked": 0,
      "closed": 5,
      "created": 5,
      "in-progress": 9
    },
    "2024-11-29": {
      "backlog": 0,
      "blocked": 0,
      "closed": 1,
      "created": 1,
      "in-progress": 9
    },
    "2024-12-06": {
      "backlog": 1,
      "blocked": 0,
      "closed": 2,
      "created": 2,
      "in-progress": 2
    },
    "2024-12-13": {
      "backlog": 1,
      "blocked": 0,
      "closed": 2,
      "created": 2,
      "in-progress": 1
    },
    "2024-12-20": {
      "backlog": 1,
      "blocked": 0,
      "closed": 3,
      "created": 3,
      "in-progress": 2
    },
    "2024-12-27": {
      "backlog": 1,
      "blocked": 0,
      "closed": 1,
      "created": 1,
      "in-progress": 2
    },
    "2025-01-03": {
      "backlog": 1,
      "blocked": 0,
      "closed": 0,
      "created": 0,
      "in-progress": 2
    },
    "2025-01-10": {
      "backlog": 0,
      "blocked": 1,
      "closed": 4,
      "created": 4,
      "in-progress": 3
    },
    "2025-01-17": {
      "backlog": 4,
      "blocked": 1,
      "closed": 4,
      "created": 4,
      "in-progress": 2
    },
    "2025-01-24": {
      "backlog": 2,
      "blocked": 1,
      "closed": 4,
      "created": 4,
      "in-progress": 3
    },
    "2025-01-31": {
      "backlog": 0,
      "blocked": 1,
      "closed": 2,
      "created": 2,
      "in-progress": 1
    },
    "2025-02-07": {
      "backlog": 1,
      "blocked": 1,
      "closed": 4,
      "created": 4,
      "in-progress": 3
    },
    "2025-02-14": {
      "backlog": 2,
      "blocked": 1,
      "closed": 5,
      "created": 5,
      "in-progress": 4
    },
    "2025-02-21": {
      "backlog": 1,
      "blocked": 1,
      "closed": 2,
      "created": 2,
      "in-progress": 4
    },
    "2025-02-28": {
      "backlog": 0,
      "blocked": 0,
      "closed": 5,
      "created": 5,
      "in-progress": 5
    },
    "2025-03-07": {
      "backlog": 1,
      "blocked": 0,
      "closed": 10,
      "created": 10,
      "in-progress": 3
    }
  },
  "jira-request-stats": {
    "2024-02-09": {
      "complete": 8.17,
      "completed": "LR-69, LR-77",
      "deadline": 0.56,
      "num_completed": 2,
      "num_triaged": 4,
      "triage": 4.36,
      "triaged": "LR-69, LR-74, LR-77, LR-78"
    },
    "2024-02-16": {
      "complete": 8.06,
      "completed": "LR-70, LR-74, LR-75, LR-78",
      "deadline": 2.18,
      "num_completed": 4,
      "num_triaged": 4,
      "triage": 7.73,
      "triaged": "LR-70, LR-74, LR-75, LR-78"
    },
    "2024-02-23": {
      "complete": 6.6,
      "completed": "LR-79, LR-81",
      "deadline": 0.32,
      "num_completed": 2,
      "num_triaged": 2,
      "triage": 5.93,
      "triaged": "LR-79, LR-81"
    },
    "2024-03-01": {
      "complete": 0,
      "completed": "",
      "deadline": 0,
      "num_completed": 0,
      "num_triaged": 0,
      "triage": 0,
      "triaged": ""
    },
    "2024-03-08": {
      "complete": 0,
      "completed": "",
      "deadline": 0,
      "num_completed": 0,
      "num_triaged": 0,
      "triage": 0,
      "triaged": ""
    },
    "2024-03-15": {
      "complete": 0,
      "completed": "",
      "deadline": 0,
      "num_completed": 0,
      "num_triaged": 1,
      "triage": 0.16,
      "triaged": "LR-82"
    },
    "2024-03-22": {
      "complete": 1.07,
      "completed": "LR-83, LR-85",
      "deadline": -5.59,
      "num_completed": 2,
      "num_triaged": 3,
      "triage": 0.87,
      "triaged": "LR-83, LR-84, LR-85"
    },
    "2024-03-29": {
      "complete": 4.45,
      "completed": "LR-86, LR-87",
      "deadline": -1.19,
      "num_completed": 2,
      "num_triaged": 3,
      "triage": 2.42,
      "triaged": "LR-86, LR-87, LR-88"
    },
    "2024-04-05": {
      "complete": 6.35,
      "completed": "LR-89",
      "deadline": -0.75,
      "num_completed": 1,
      "num_triaged": 1,
      "triage": 1.01,
      "triaged": "LR-89"
    },
    "2024-04-12": {
      "complete": 0,
      "completed": "",
      "deadline": 0,
      "num_completed": 0,
      "num_triaged": 2,
      "triage": 0.93,
      "triaged": "LR-90, LR-91"
    },
    "2024-04-19": {
      "complete": 0.88,
      "completed": "LR-94",
      "deadline": -1.33,
      "num_completed": 1,
      "num_triaged": 3,
      "triage": 1.59,
      "triaged": "LR-92, LR-93, LR-94"
    },
    "2024-04-26": {
      "complete": 0,
      "completed": "",
      "deadline": 0,
      "num_completed": 0,
      "num_triaged": 1,
      "triage": 1.09,
      "triaged": "LR-95"
    },
    "2024-05-03": {
      "complete": 4.44,
      "completed": "LR-95, LR-96",
      "deadline": -2.84,
      "num_completed": 2,
      "num_triaged": 2,
      "triage": 3.12,
      "triaged": "LR-95, LR-96"
    },
    "2024-05-10": {
      "complete": 3.74,
      "completed": "LR-100, LR-97",
      "deadline": -2.96,
      "num_completed": 2,
      "num_triaged": 4,
      "triage": 1.87,
      "triaged": "LR-100, LR-97, LR-98, LR-99"
    },
    "2024-05-17": {
      "complete": 0,
      "completed": "",
      "deadline": 0,
      "num_completed": 0,
      "num_triaged": 1,
      "triage": 3.03,
      "triaged": "LR-101"
    },
    "2024-05-24": {
      "complete": 2.33,
      "completed": "LR-104",
      "deadline": -2.09,
      "num_completed": 1,
      "num_triaged": 4,
      "triage": 1.84,
      "triaged": "LR-102, LR-103, LR-104, LR-106"
    },
    "2024-05-31": {
      "complete": 7.27,
      "completed": "LR-105",
      "deadline": 5.34,
      "num_completed": 1,
      "num_triaged": 2,
      "triage": 3.4,
      "triaged": "LR-105, LR-107"
    },
    "2024-06-07": {
      "complete": 5.2,
      "completed": "LR-108",
      "deadline": -3.12,
      "num_completed": 1,
      "num_triaged": 1,
      "triage": 2.32,
      "triaged": "LR-108"
    },
    "2024-06-14": {
      "complete": 1.32,
      "completed": "LR-109",
      "deadline": -0.79,
      "num_completed": 1,
      "num_triaged": 2,
      "triage": 0.8,
      "triaged": "LR-109, LR-111"
    },
    "2024-06-21": {
      "complete": 0,
      "completed": "",
      "deadline": 0,
      "num_completed": 0,
      "num_triaged": 1,
      "triage": 5.32,
      "triaged": "LR-112"
    },
    "2024-06-28": {
      "complete": 3.1,
      "completed": "LR-113, LR-114",
      "deadline": -2.57,
      "num_completed": 2,
      "num_triaged": 2,
      "triage": 0.28,
      "triaged": "LR-113, LR-114"
    },
    "2024-07-05": {
      "complete": 0,
      "completed": "",
      "deadline": 0,
      "num_completed": 0,
      "num_triaged": 0,
      "triage": 0,
      "triaged": ""
    },
    "2024-07-12": {
      "complete": 0,
      "completed": "",
      "deadline": 0,
      "num_completed": 0,
      "num_triaged": 0,
      "triage": 0,
      "triaged": ""
    },
    "2024-07-19": {
      "complete": 1.44,
      "completed": "LR-116, LR-117",
      "deadline": -1.31,
      "num_completed": 2,
      "num_triaged": 2,
      "triage": 0.1,
      "triaged": "LR-116, LR-117"
    },
    "2024-07-26": {
      "complete": 0.73,
      "completed": "LR-123",
      "deadline": -6.35,
      "num_completed": 1,
      "num_triaged": 6,
      "triage": 2.06,
      "triaged": "LR-118, LR-119, LR-120, LR-121, LR-122, LR-123"
    },
    "2024-08-02": {
      "complete": 0.34,
      "completed": "LR-125",
      "deadline": -7.31,
      "num_completed": 1,
      "num_triaged": 1,
      "triage": 0.34,
      "triaged": "LR-125"
    },
    "2024-08-09": {
      "complete": 0,
      "completed": "",
      "deadline": 0,
      "num_completed": 0,
      "num_triaged": 3,
      "triage": 1.48,
      "triaged": "LR-124, LR-126, LR-129"
    },
    "2024-08-16": {
      "complete": 0,
      "completed": "",
      "deadline": 0,
      "num_completed": 0,
      "num_triaged": 0,
      "triage": 0,
      "triaged": ""
    },
    "2024-08-23": {
      "complete": 0,
      "completed": "",
      "deadline": 0,
      "num_completed": 0,
      "num_triaged": 1,
      "triage": 0.01,
      "triaged": "LR-130"
    },
    "2024-08-30": {
      "complete": 0,
      "completed": "",
      "deadline": 0,
      "num_completed": 0,
      "num_triaged": 0,
      "triage": 0,
      "triaged": ""
    },
    "2024-09-06": {
      "complete": 6.12,
      "completed": "LR-131",
      "deadline": -8.21,
      "num_completed": 1,
      "num_triaged": 3,
      "triage": 2.46,
      "triaged": "LR-131, LR-132, LR-133"
    },
    "2024-09-13": {
      "complete": 0,
      "completed": "",
      "deadline": 0,
      "num_completed": 0,
      "num_triaged": 1,
      "triage": 1.18,
      "triaged": "LR-134"
    },
    "2024-09-20": {
      "complete": 1.21,
      "completed": "LR-135, LR-136",
      "deadline": -1.44,
      "num_completed": 2,
      "num_triaged": 3,
      "triage": 0.35,
      "triaged": "LR-135, LR-136, LR-137"
    },
    "2024-09-27": {
      "complete": 0.16,
      "completed": "LR-139, LR-140",
      "deadline": -1.08,
      "num_completed": 2,
      "num_triaged": 4,
      "triage": 0.11,
      "triaged": "LR-138, LR-139, LR-140, LR-141"
    },
    "2024-10-04": {
      "complete": 0,
      "completed": "",
      "deadline": 0,
      "num_completed": 0,
      "num_triaged": 1,
      "triage": 0.06,
      "triaged": "LR-142"
    },
    "2024-10-11": {
      "complete": 6.33,
      "completed": "LR-143",
      "deadline": 2.98,
      "num_completed": 1,
      "num_triaged": 3,
      "triage": 2.76,
      "triaged": "LR-143, LR-144, LR-145"
    },
    "2024-10-18": {
      "complete": 5.0,
      "completed": "LR-146",
      "deadline": -0.23,
      "num_completed": 1,
      "num_triaged": 3,
      "triage": 0.21,
      "triaged": "LR-146, LR-147, LR-148"
    },
    "2024-10-25": {
      "complete": 0,
      "completed": "",
      "deadline": 0,
      "num_completed": 0,
      "num_triaged": 2,
      "triage": 1.29,
      "triaged": "LR-149, LR-150"
    },
    "2024-11-01": {
      "complete": 0.99,
      "completed": "LR-152",
      "deadline": -6.25,
      "num_completed": 1,
      "num_triaged": 2,
      "triage": 0.18,
      "triaged": "LR-151, LR-152"
    },
    "2024-11-08": {
      "complete": 0,
      "completed": "",
      "deadline": 0,
      "num_completed": 0,
      "num_triaged": 5,
      "triage": 0.46,
      "triaged": "LR-153, LR-154, LR-155, LR-156, LR-157"
    },
    "2024-11-15": {
      "complete": 0,
      "completed": "",
      "deadline": 0,
      "num_completed": 0,
      "num_triaged": 0,
      "triage": 0,
      "triaged": ""
    },
    "2024-11-22": {
      "complete": 1.93,
      "completed": "LR-161, LR-162",
      "deadline": -2.8,
      "num_completed": 2,
      "num_triaged": 5,
      "triage": 1.92,
      "triaged": "LR-158, LR-159, LR-160, LR-161, LR-162"
    },
    "2024-11-29": {
      "complete": 0,
      "completed": "",
      "deadline": 0,
      "num_completed": 0,
      "num_triaged": 1,
      "triage": 0.43,
      "triaged": "LR-163"
    },
    "2024-12-06": {
      "complete": 0,
      "completed": "",
      "deadline": 0,
      "num_completed": 0,
      "num_triaged": 0,
      "triage": 0,
      "triaged": ""
    },
    "2024-12-13": {
      "complete": 5.25,
      "completed": "LR-164",
      "deadline": -2.11,
      "num_completed": 1,
      "num_triaged": 1,
      "triage": 2.28,
      "triaged": "LR-164"
    },
    "2024-12-20": {
      "complete": 4.12,
      "completed": "LR-165",
      "deadline": 0.89,
      "num_completed": 1,
      "num_triaged": 1,
      "triage": 4.12,
      "triaged": "LR-165"
    },
    "2024-12-27": {
      "complete": 0,
      "completed": "",
      "deadline": 0,
      "num_completed": 0,
      "num_triaged": 1,
      "triage": 0.33,
      "triaged": "LR-167"
    },
    "2025-01-03": {
      "complete": 0,
      "completed": "",
      "deadline": 0,
      "num_completed": 0,
      "num_triaged": 0,
      "triage": 0,
      "triaged": ""
    },
    "2025-01-10": {
      "complete": 1.16,
      "completed": "LR-168",
      "deadline": -2.13,
      "num_completed": 1,
      "num_triaged": 3,
      "triage": 0.52,
      "triaged": "LR-168, LR-169, LR-170"
    },
    "2025-01-17": {
      "complete": 0,
      "completed": "",
      "deadline": 0,
      "num_completed": 0,
      "num_triaged": 0,
      "triage": 0,
      "triaged": ""
    },
    "2025-01-24": {
      "complete": 6.22,
      "completed": "LR-171, LR-172, LR-173, LR-174",
      "deadline": -0.96,
      "num_completed": 4,
      "num_triaged": 4,
      "triage": 2.88,
      "triaged": "LR-171, LR-172, LR-173, LR-174"
    },
    "2025-01-31": {
      "complete": 3.55,
      "completed": "LR-175, LR-176",
      "deadline": -0.14,
      "num_completed": 2,
      "num_triaged": 2,
      "triage": 0.72,
      "triaged": "LR-175, LR-176"
    },
    "2025-02-07": {
      "complete": 1.16,
      "completed": "LR-177, LR-178",
      "deadline": -5.85,
      "num_completed": 2,
      "num_triaged": 3,
      "triage": 0.77,
      "triaged": "LR-177, LR-178, LR-179"
    },
    "2025-02-14": {
      "complete": 0.17,
      "completed": "LR-180",
      "deadline": -2.9,
      "num_completed": 1,
      "num_triaged": 2,
      "triage": 0.23,
      "triaged": "LR-180, LR-181"
    },
    "2025-02-21": {
      "complete": 2.69,
      "completed": "LR-182, LR-183",
      "deadline": -4.5,
      "num_completed": 2,
      "num_triaged": 3,
      "triage": 0.5,
      "triaged": "LR-182, LR-183, LR-184"
    },
    "2025-02-28": {
      "complete": 3.47,
      "completed": "LR-184, LR-185, LR-187",
      "deadline": -0.05,
      "num_completed": 3,
      "num_triaged": 4,
      "triage": 2.12,
      "triaged": "LR-184, LR-185, LR-186, LR-187"
    },
    "2025-03-07": {
      "complete": 1.6,
      "completed": "LR-188, LR-189, LR-190, LR-193, LR-194",
      "deadline": -2.62,
      "num_completed": 5,
      "num_triaged": 6,
      "triage": 0.39,
      "triaged": "LR-188, LR-189, LR-190, LR-192, LR-193, LR-194"
    }
  },
  "jira-vendor-stats": {
    "2024-02-09": {
      "deadline": -3.28,
      "deliver": 1.86,
      "delivered": "L10NV-175",
      "num_delivered": 1,
      "num_triaged": 1,
      "triage": 0.53,
      "triaged": "L10NV-176"
    },
    "2024-02-16": {
      "deadline": -0.4,
      "deliver": 9.04,
      "delivered": "L10NV-176",
      "num_delivered": 1,
      "num_triaged": 2,
      "triage": 0.04,
      "triaged": "L10NV-178, L10NV-179"
    },
    "2024-02-23": {
      "deadline": 2.42,
      "deliver": 8.12,
      "delivered": "L10NV-174, L10NV-177, L10NV-178, L10NV-179, L10NV-180, L10NV-181",
      "num_delivered": 6,
      "num_triaged": 2,
      "triage": 0.74,
      "triaged": "L10NV-180, L10NV-181"
    },
    "2024-03-01": {
      "deadline": -0.24,
      "deliver": 5.92,
      "delivered": "L10NV-183",
      "num_delivered": 1,
      "num_triaged": 2,
      "triage": 0.17,
      "triaged": "L10NV-182, L10NV-183"
    },
    "2024-03-08": {
      "deadline": 0.65,
      "deliver": 7.0,
      "delivered": "L10NV-182",
      "num_delivered": 1,
      "num_triaged": 1,
      "triage": 0.05,
      "triaged": "L10NV-184"
    },
    "2024-03-15": {
      "deadline": -1.34,
      "deliver": 2.86,
      "delivered": "L10NV-185",
      "num_delivered": 1,
      "num_triaged": 3,
      "triage": 0.3,
      "triaged": "L10NV-184, L10NV-185, L10NV-186"
    },
    "2024-03-22": {
      "deadline": -0.22,
      "deliver": 5.91,
      "delivered": "L10NV-184, L10NV-187",
      "num_delivered": 2,
      "num_triaged": 6,
      "triage": 0.06,
      "triaged": "L10NV-187, L10NV-188, L10NV-189, L10NV-190, L10NV-191, L10NV-192"
    },
    "2024-03-29": {
      "deadline": -1.9,
      "deliver": 5.67,
      "delivered": "L10NV-186, L10NV-188, L10NV-191",
      "num_delivered": 3,
      "num_triaged": 5,
      "triage": 0.41,
      "triaged": "L10NV-189, L10NV-191, L10NV-193, L10NV-197, L10NV-198"
    },
    "2024-04-05": {
      "deadline": -1.62,
      "deliver": 5.65,
      "delivered": "L10NV-197, L10NV-198",
      "num_delivered": 2,
      "num_triaged": 1,
      "triage": 0.32,
      "triaged": "L10NV-199"
    },
    "2024-04-12": {
      "deadline": 0.6,
      "deliver": 11.59,
      "delivered": "L10NV-189, L10NV-190, L10NV-192, L10NV-193, L10NV-199, L10NV-200",
      "num_delivered": 6,
      "num_triaged": 3,
      "triage": 0.01,
      "triaged": "L10NV-200, L10NV-201, L10NV-202"
    },
    "2024-04-19": {
      "deadline": -0.35,
      "deliver": 9.96,
      "delivered": "L10NV-201, L10NV-202",
      "num_delivered": 2,
      "num_triaged": 0,
      "triage": 0,
      "triaged": ""
    },
    "2024-04-26": {
      "deadline": 0,
      "deliver": 0,
      "delivered": "",
      "num_delivered": 0,
      "num_triaged": 0,
      "triage": 0,
      "triaged": ""
    },
    "2024-05-03": {
      "deadline": -4.34,
      "deliver": 2.87,
      "delivered": "L10NV-203",
      "num_delivered": 1,
      "num_triaged": 1,
      "triage": 0.01,
      "triaged": "L10NV-203"
    },
    "2024-05-10": {
      "deadline": 0,
      "deliver": 0,
      "delivered": "",
      "num_delivered": 0,
      "num_triaged": 0,
      "triage": 0,
      "triaged": ""
    },
    "2024-05-17": {
      "deadline": -8.27,
      "deliver": 4.53,
      "delivered": "L10NV-204, L10NV-205",
      "num_delivered": 2,
      "num_triaged": 1,
      "triage": 0.02,
      "triaged": "L10NV-204"
    },
    "2024-05-24": {
      "deadline": -0.36,
      "deliver": 5.0,
      "delivered": "L10NV-206",
      "num_delivered": 1,
      "num_triaged": 2,
      "triage": 0.06,
      "triaged": "L10NV-206, L10NV-207"
    },
    "2024-05-31": {
      "deadline": -2.29,
      "deliver": 4.0,
      "delivered": "L10NV-207",
      "num_delivered": 1,
      "num_triaged": 1,
      "triage": 0.12,
      "triaged": "L10NV-208"
    },
    "2024-06-07": {
      "deadline": -1.32,
      "deliver": 4.14,
      "delivered": "L10NV-208",
      "num_delivered": 1,
      "num_triaged": 1,
      "triage": 0.0,
      "triaged": "L10NV-209"
    },
    "2024-06-14": {
      "deadline": 4.68,
      "deliver": 11.94,
      "delivered": "L10NV-209",
      "num_delivered": 1,
      "num_triaged": 0,
      "triage": 0,
      "triaged": ""
    },
    "2024-06-21": {
      "deadline": -1.33,
      "deliver": 2.78,
      "delivered": "L10NV-211",
      "num_delivered": 1,
      "num_triaged": 2,
      "triage": 0.14,
      "triaged": "L10NV-211, L10NV-212"
    },
    "2024-06-28": {
      "deadline": 0.19,
      "deliver": 2.46,
      "delivered": "L10NV-212, L10NV-213",
      "num_delivered": 2,
      "num_triaged": 3,
      "triage": 0.04,
      "triaged": "L10NV-213, L10NV-214, L10NV-215"
    },
    "2024-07-05": {
      "deadline": 0,
      "deliver": 0,
      "delivered": "",
      "num_delivered": 0,
      "num_triaged": 3,
      "triage": 0.56,
      "triaged": "L10NV-214, L10NV-215, L10NV-216"
    },
    "2024-07-12": {
      "deadline": 2.63,
      "deliver": 6.12,
      "delivered": "L10NV-216",
      "num_delivered": 1,
      "num_triaged": 2,
      "triage": 0.1,
      "triaged": "L10NV-217, L10NV-218"
    },
    "2024-07-19": {
      "deadline": -11.62,
      "deliver": 2.68,
      "delivered": "L10NV-218, L10NV-219",
      "num_delivered": 2,
      "num_triaged": 1,
      "triage": 0.0,
      "triaged": "L10NV-219"
    },
    "2024-07-26": {
      "deadline": 0,
      "deliver": 0,
      "delivered": "",
      "num_delivered": 0,
      "num_triaged": 1,
      "triage": 0.0,
      "triaged": "L10NV-220"
    },
    "2024-08-02": {
      "deadline": -0.31,
      "deliver": 8.01,
      "delivered": "L10NV-220",
      "num_delivered": 1,
      "num_triaged": 3,
      "triage": 0.06,
      "triaged": "L10NV-221, L10NV-222, L10NV-223"
    },
    "2024-08-09": {
      "deadline": -1.19,
      "deliver": 3.63,
      "delivered": "L10NV-221, L10NV-222, L10NV-224",
      "num_delivered": 3,
      "num_triaged": 0,
      "triage": 0,
      "triaged": ""
    },
    "2024-08-16": {
      "deadline": 0,
      "deliver": 0,
      "delivered": "",
      "num_delivered": 0,
      "num_triaged": 0,
      "triage": 0,
      "triaged": ""
    },
    "2024-08-23": {
      "deadline": 0,
      "deliver": 0,
      "delivered": "",
      "num_delivered": 0,
      "num_triaged": 0,
      "triage": 0,
      "triaged": ""
    },
    "2024-08-30": {
      "deadline": -6.17,
      "deliver": 5.35,
      "delivered": "L10NV-225, L10NV-226",
      "num_delivered": 2,
      "num_triaged": 4,
      "triage": 0.19,
      "triaged": "L10NV-225, L10NV-226, L10NV-227, L10NV-228"
    },
    "2024-09-06": {
      "deadline": 8.67,
      "deliver": 13.45,
      "delivered": "L10NV-223, L10NV-228, L10NV-229",
      "num_delivered": 3,
      "num_triaged": 1,
      "triage": 0.0,
      "triaged": "L10NV-230"
    },
    "2024-09-13": {
      "deadline": -2.37,
      "deliver": 1.12,
      "delivered": "L10NV-231",
      "num_delivered": 1,
      "num_triaged": 3,
      "triage": 0.1,
      "triaged": "L10NV-231, L10NV-232, L10NV-233"
    },
    "2024-09-20": {
      "deadline": -1.65,
      "deliver": 2.79,
      "delivered": "L10NV-232, L10NV-233, L10NV-235, L10NV-236, L10NV-237",
      "num_delivered": 5,
      "num_triaged": 5,
      "triage": 0.19,
      "triaged": "L10NV-234, L10NV-235, L10NV-236, L10NV-237, L10NV-238"
    },
    "2024-09-27": {
      "deadline": -0.28,
      "deliver": 7.88,
      "delivered": "L10NV-234",
      "num_delivered": 1,
      "num_triaged": 0,
      "triage": 0,
      "triaged": ""
    },
    "2024-10-04": {
      "deadline": -0.82,
      "deliver": 3.85,
      "delivered": "L10NV-239, L10NV-240",
      "num_delivered": 2,
      "num_triaged": 2,
      "triage": 1.45,
      "triaged": "L10NV-239, L10NV-240"
    },
    "2024-10-11": {
      "deadline": 0,
      "deliver": 0,
      "delivered": "",
      "num_delivered": 0,
      "num_triaged": 1,
      "triage": 8.42,
      "triaged": "L10NV-241"
    },
    "2024-10-18": {
      "deadline": -3.58,
      "deliver": 5.1,
      "delivered": "L10NV-241, L10NV-242, L10NV-244, L10NV-245",
      "num_delivered": 4,
      "num_triaged": 4,
      "triage": 0.57,
      "triaged": "L10NV-242, L10NV-243, L10NV-244, L10NV-245"
    },
    "2024-10-25": {
      "deadline": -2.78,
      "deliver": 6.16,
      "delivered": "L10NV-243, L10NV-248, L10NV-249, L10NV-250",
      "num_delivered": 4,
      "num_triaged": 5,
      "triage": 0.77,
      "triaged": "L10NV-247, L10NV-248, L10NV-249, L10NV-250, L10NV-251"
    },
    "2024-11-01": {
      "deadline": -2.92,
      "deliver": 5.85,
      "delivered": "L10NV-246, L10NV-247, L10NV-251, L10NV-252, L10NV-253",
      "num_delivered": 5,
      "num_triaged": 3,
      "triage": 18.41,
      "triaged": "L10NV-230, L10NV-253, L10NV-254"
    },
    "2024-11-08": {
      "deadline": 0,
      "deliver": 0,
      "delivered": "",
      "num_delivered": 0,
      "num_triaged": 1,
      "triage": 1.05,
      "triaged": "L10NV-254"
    },
    "2024-11-15": {
      "deadline": 0.52,
      "deliver": 39.81,
      "delivered": "L10NV-230, L10NV-255",
      "num_delivered": 2,
      "num_triaged": 1,
      "triage": 0.0,
      "triaged": "L10NV-256"
    },
    "2024-11-22": {
      "deadline": -11.21,
      "deliver": 2.8,
      "delivered": "L10NV-257",
      "num_delivered": 1,
      "num_triaged": 0,
      "triage": 0,
      "triaged": ""
    },
    "2024-11-29": {
      "deadline": 0,
      "deliver": 0,
      "delivered": "",
      "num_delivered": 0,
      "num_triaged": 0,
      "triage": 0,
      "triaged": ""
    },
    "2024-12-06": {
      "deadline": 0,
      "deliver": 0,
      "delivered": "",
      "num_delivered": 0,
      "num_triaged": 0,
      "triage": 0,
      "triaged": ""
    },
    "2024-12-13": {
      "deadline": 7.42,
      "deliver": 21.14,
      "delivered": "L10NV-254, L10NV-259",
      "num_delivered": 2,
      "num_triaged": 2,
      "triage": 0.0,
      "triaged": "L10NV-259, L10NV-260"
    },
    "2024-12-20": {
      "deadline": -0.25,
      "deliver": 5.9,
      "delivered": "L10NV-260",
      "num_delivered": 1,
      "num_triaged": 0,
      "triage": 0,
      "triaged": ""
    },
    "2024-12-27": {
      "deadline": -0.27,
      "deliver": 7.03,
      "delivered": "L10NV-261",
      "num_delivered": 1,
      "num_triaged": 0,
      "triage": 0,
      "triaged": ""
    },
    "2025-01-03": {
      "deadline": 0,
      "deliver": 0,
      "delivered": "",
      "num_delivered": 0,
      "num_triaged": 0,
      "triage": 0,
      "triaged": ""
    },
    "2025-01-10": {
      "deadline": -1.26,
      "deliver": 4.99,
      "delivered": "L10NV-262",
      "num_delivered": 1,
      "num_triaged": 1,
      "triage": 0.01,
      "triaged": "L10NV-262"
    },
    "2025-01-17": {
      "deadline": 0,
      "deliver": 0,
      "delivered": "",
      "num_delivered": 0,
      "num_triaged": 0,
      "triage": 0,
      "triaged": ""
    },
    "2025-01-24": {
      "deadline": 0,
      "deliver": 0,
      "delivered": "",
      "num_delivered": 0,
      "num_triaged": 2,
      "triage": 0.85,
      "triaged": "L10NV-263, L10NV-264"
    },
    "2025-01-31": {
      "deadline": -5.2,
      "deliver": 7.24,
      "delivered": "L10NV-263, L10NV-264, L10NV-266",
      "num_delivered": 3,
      "num_triaged": 1,
      "triage": 0.27,
      "triaged": "L10NV-266"
    },
    "2025-02-07": {
      "deadline": 0,
      "deliver": 0,
      "delivered": "",
      "num_delivered": 0,
      "num_triaged": 0,
      "triage": 0,
      "triaged": ""
    },
    "2025-02-14": {
      "deadline": 0,
      "deliver": 0,
      "delivered": "",
      "num_delivered": 0,
      "num_triaged": 3,
      "triage": 2.15,
      "triaged": "L10NV-267, L10NV-268, L10NV-269"
    },
    "2025-02-21": {
      "deadline": -1.3,
      "deliver": 5.26,
      "delivered": "L10NV-269",
      "num_delivered": 1,
      "num_triaged": 0,
      "triage": 0,
      "triaged": ""
    },
    "2025-02-28": {
      "deadline": -0.43,
      "deliver": 28.66,
      "delivered": "L10NV-263, L10NV-267",
      "num_delivered": 2,
      "num_triaged": 1,
      "triage": 0.22,
      "triaged": "L10NV-270"
    },
    "2025-03-07": {
      "deadline": -4.54,
      "deliver": 6.7,
      "delivered": "L10NV-268, L10NV-270, L10NV-271, L10NV-272",
      "num_delivered": 4,
      "num_triaged": 3,
      "triage": 0.11,
      "triaged": "L10NV-271, L10NV-272, L10NV-273"
    }
  },
  "pontoon-issues": {
    "2024-02-09": {
      "P1": 1,
      "P2": 39,
      "P3": 238,
      "P4": 44,
      "P5": 22,
      "Total": 344,
      "Untriaged": 0,
      "avg-time-to-close": 1.4,
      "closed": 1,
      "opened": 9
    },
    "2024-02-16": {
      "P1": 1,
      "P2": 38,
      "P3": 237,
      "P4": 44,
      "P5": 22,
      "Total": 342,
      "Untriaged": 0,
      "avg-time-to-close": 391.3,
      "closed": 7,
      "opened": 5
    },
    "2024-02-23": {
      "P1": 1,
      "P2": 38,
      "P3": 238,
      "P4": 46,
      "P5": 22,
      "Total": 345,
      "Untriaged": 0,
      "avg-time-to-close": 6657.4,
      "closed": 4,
      "opened": 7
    },
    "2024-03-01": {
      "P1": 2,
      "P2": 36,
      "P3": 238,
      "P4": 46,
      "P5": 22,
      "Total": 344,
      "Untriaged": 0,
      "avg-time-to-close": 1114.3,
      "closed": 4,
      "opened": 3
    },
    "2024-03-08": {
      "P1": 0,
      "P2": 37,
      "P3": 237,
      "P4": 46,
      "P5": 22,
      "Total": 342,
      "Untriaged": 0,
      "avg-time-to-close": 2506.3,
      "closed": 2,
      "opened": 0
    },
    "2024-03-15": {
      "P1": 0,
      "P2": 35,
      "P3": 234,
      "P4": 46,
      "P5": 23,
      "Total": 338,
      "Untriaged": 0,
      "avg-time-to-close": 4373.0,
      "closed": 10,
      "opened": 6
    },
    "2024-03-22": {
      "P1": 0,
      "P2": 34,
      "P3": 234,
      "P4": 46,
      "P5": 23,
      "Total": 338,
      "Untriaged": 1,
      "avg-time-to-close": 26324.1,
      "closed": 1,
      "opened": 1
    },
    "2024-03-29": {
      "P1": 0,
      "P2": 32,
      "P3": 236,
      "P4": 46,
      "P5": 23,
      "Total": 337,
      "Untriaged": 0,
      "avg-time-to-close": 8894.5,
      "closed": 4,
      "opened": 3
    },
    "2024-04-05": {
      "P1": 0,
      "P2": 33,
      "P3": 225,
      "P4": 49,
      "P5": 24,
      "Total": 332,
      "Untriaged": 1,
      "avg-time-to-close": 26102.9,
      "closed": 10,
      "opened": 5
    },
    "2024-04-12": {
      "P1": 0,
      "P2": 32,
      "P3": 224,
      "P4": 50,
      "P5": 24,
      "Total": 330,
      "Untriaged": 0,
      "avg-time-to-close": 664.2,
      "closed": 3,
      "opened": 1
    },
    "2024-04-19": {
      "P1": 0,
      "P2": 31,
      "P3": 224,
      "P4": 49,
      "P5": 24,
      "Total": 328,
      "Untriaged": 0,
      "avg-time-to-close": 1381.1,
      "closed": 5,
      "opened": 3
    },
    "2024-04-26": {
      "P1": 0,
      "P2": 30,
      "P3": 224,
      "P4": 48,
      "P5": 24,
      "Total": 326,
      "Untriaged": 0,
      "avg-time-to-close": 19822.8,
      "closed": 3,
      "opened": 1
    },
    "2024-05-03": {
      "P1": 0,
      "P2": 29,
      "P3": 225,
      "P4": 48,
      "P5": 24,
      "Total": 327,
      "Untriaged": 1,
      "avg-time-to-close": 9392.4,
      "closed": 4,
      "opened": 5
    },
    "2024-05-10": {
      "P1": 0,
      "P2": 31,
      "P3": 225,
      "P4": 48,
      "P5": 24,
      "Total": 329,
      "Untriaged": 1,
      "avg-time-to-close": 155.8,
      "closed": 3,
      "opened": 5
    },
    "2024-05-17": {
      "P1": 0,
      "P2": 32,
      "P3": 225,
      "P4": 47,
      "P5": 24,
      "Total": 334,
      "Untriaged": 6,
      "avg-time-to-close": 2828.5,
      "closed": 8,
      "opened": 13
    },
    "2024-05-24": {
      "P1": 0,
      "P2": 31,
      "P3": 228,
      "P4": 47,
      "P5": 24,
      "Total": 336,
      "Untriaged": 6,
      "avg-time-to-close": 143.6,
      "closed": 1,
      "opened": 4
    },
    "2024-05-31": {
      "P1": 0,
      "P2": 39,
      "P3": 228,
      "P4": 47,
      "P5": 24,
      "Total": 339,
      "Untriaged": 1,
      "avg-time-to-close": 9234.9,
      "closed": 4,
      "opened": 7
    },
    "2024-06-07": {
      "P1": 0,
      "P2": 39,
      "P3": 227,
      "P4": 47,
      "P5": 24,
      "Total": 338,
      "Untriaged": 1,
      "avg-time-to-close": 4740.3,
      "closed": 2,
      "opened": 1
    },
    "2024-06-14": {
      "P1": 0,
      "P2": 39,
      "P3": 227,
      "P4": 47,
      "P5": 24,
      "Total": 338,
      "Untriaged": 1,
      "avg-time-to-close": 15217.8,
      "closed": 1,
      "opened": 1
    },
    "2024-06-21": {
      "P1": 0,
      "P2": 39,
      "P3": 226,
      "P4": 47,
      "P5": 24,
      "Total": 337,
      "Untriaged": 1,
      "avg-time-to-close": 22868.5,
      "closed": 1,
      "opened": 0
    },
    "2024-06-28": {
      "P1": 1,
      "P2": 39,
      "P3": 226,
      "P4": 47,
      "P5": 24,
      "Total": 339,
      "Untriaged": 2,
      "avg-time-to-close": 0.0,
      "closed": 0,
      "opened": 2
    },
    "2024-07-05": {
      "P1": 0,
      "P2": 39,
      "P3": 226,
      "P4": 47,
      "P5": 25,
      "Total": 338,
      "Untriaged": 1,
      "avg-time-to-close": 12458.0,
      "closed": 6,
      "opened": 5
    },
    "2024-07-12": {
      "P1": 0,
      "P2": 39,
      "P3": 226,
      "P4": 47,
      "P5": 25,
      "Total": 338,
      "Untriaged": 1,
      "avg-time-to-close": 124.7,
      "closed": 2,
      "opened": 2
    },
    "2024-07-19": {
      "P1": 0,
      "P2": 39,
      "P3": 226,
      "P4": 47,
      "P5": 24,
      "Total": 337,
      "Untriaged": 1,
      "avg-time-to-close": 982.4,
      "closed": 2,
      "opened": 1
    },
    "2024-07-26": {
      "P1": 0,
      "P2": 39,
      "P3": 226,
      "P4": 47,
      "P5": 24,
      "Total": 337,
      "Untriaged": 1,
      "avg-time-to-close": 9501.6,
      "closed": 2,
      "opened": 2
    },
    "2024-08-02": {
      "P1": 0,
      "P2": 39,
      "P3": 228,
      "P4": 47,
      "P5": 24,
      "Total": 339,
      "Untriaged": 1,
      "avg-time-to-close": 210.5,
      "closed": 2,
      "opened": 4
    },
    "2024-08-09": {
      "P1": 0,
      "P2": 39,
      "P3": 228,
      "P4": 47,
      "P5": 24,
      "Total": 339,
      "Untriaged": 1,
      "avg-time-to-close": 0.0,
      "closed": 0,
      "opened": 0
    },
    "2024-08-16": {
      "P1": 0,
      "P2": 39,
      "P3": 229,
      "P4": 47,
      "P5": 24,
      "Total": 340,
      "Untriaged": 1,
      "avg-time-to-close": 526.4,
      "closed": 1,
      "opened": 2
    },
    "2024-08-23": {
      "P1": 0,
      "P2": 39,
      "P3": 227,
      "P4": 47,
      "P5": 25,
      "Total": 339,
      "Untriaged": 1,
      "avg-time-to-close": 2264.2,
      "closed": 1,
      "opened": 0
    },
    "2024-08-30": {
      "P1": 0,
      "P2": 39,
      "P3": 229,
      "P4": 47,
      "P5": 25,
      "Total": 342,
      "Untriaged": 2,
      "avg-time-to-close": 2716.5,
      "closed": 1,
      "opened": 4
    },
    "2024-09-06": {
      "P1": 0,
      "P2": 37,
      "P3": 230,
      "P4": 47,
      "P5": 25,
      "Total": 341,
      "Untriaged": 2,
      "avg-time-to-close": 1870.0,
      "closed": 3,
      "opened": 2
    },
    "2024-09-13": {
      "P1": 0,
      "P2": 37,
      "P3": 229,
      "P4": 47,
      "P5": 25,
      "Total": 339,
      "Untriaged": 1,
      "avg-time-to-close": 8759.2,
      "closed": 8,
      "opened": 6
    },
    "2024-09-20": {
      "P1": 0,
      "P2": 33,
      "P3": 233,
      "P4": 47,
      "P5": 25,
      "Total": 343,
      "Untriaged": 5,
      "avg-time-to-close": 1074.7,
      "closed": 6,
      "opened": 10
    },
    "2024-09-27": {
      "P1": 0,
      "P2": 32,
      "P3": 232,
      "P4": 46,
      "P5": 24,
      "Total": 336,
      "Untriaged": 2,
      "avg-time-to-close": 14846.2,
      "closed": 12,
      "opened": 5
    },
    "2024-10-04": {
      "P1": 0,
      "P2": 34,
      "P3": 232,
      "P4": 45,
      "P5": 24,
      "Total": 337,
      "Untriaged": 2,
      "avg-time-to-close": 5784.5,
      "closed": 6,
      "opened": 7
    },
    "2024-10-11": {
      "P1": 0,
      "P2": 34,
      "P3": 232,
      "P4": 46,
      "P5": 24,
      "Total": 338,
      "Untriaged": 2,
      "avg-time-to-close": 2.6,
      "closed": 1,
      "opened": 2
    },
    "2024-10-18": {
      "P1": 0,
      "P2": 34,
      "P3": 232,
      "P4": 46,
      "P5": 24,
      "Total": 338,
      "Untriaged": 2,
      "avg-time-to-close": 290.4,
      "closed": 1,
      "opened": 1
    },
    "2024-10-25": {
      "P1": 0,
      "P2": 35,
      "P3": 232,
      "P4": 47,
      "P5": 24,
      "Total": 342,
      "Untriaged": 4,
      "avg-time-to-close": 0.6,
      "closed": 2,
      "opened": 6
    },
    "2024-11-01": {
      "P1": 0,
      "P2": 33,
      "P3": 233,
      "P4": 47,
      "P5": 24,
      "Total": 342,
      "Untriaged": 5,
      "avg-time-to-close": 570.8,
      "closed": 2,
      "opened": 2
    },
    "2024-11-08": {
      "P1": 0,
      "P2": 32,
      "P3": 234,
      "P4": 46,
      "P5": 24,
      "Total": 340,
      "Untriaged": 4,
      "avg-time-to-close": 23162.1,
      "closed": 3,
      "opened": 1
    },
    "2024-11-15": {
      "P1": 0,
      "P2": 34,
      "P3": 235,
      "P4": 47,
      "P5": 25,
      "Total": 344,
      "Untriaged": 3,
      "avg-time-to-close": 6.6,
      "closed": 1,
      "opened": 5
    },
    "2024-11-22": {
      "P1": 0,
      "P2": 32,
      "P3": 238,
      "P4": 47,
      "P5": 25,
      "Total": 345,
      "Untriaged": 3,
      "avg-time-to-close": 5759.1,
      "closed": 6,
      "opened": 7
    },
    "2024-11-29": {
      "P1": 0,
      "P2": 32,
      "P3": 239,
      "P4": 44,
      "P5": 25,
      "Total": 341,
      "Untriaged": 1,
      "avg-time-to-close": 52680.4,
      "closed": 4,
      "opened": 0
    },
    "2024-12-06": {
      "P1": 0,
      "P2": 32,
      "P3": 239,
      "P4": 44,
      "P5": 25,
      "Total": 340,
      "Untriaged": 0,
      "avg-time-to-close": 37794.2,
      "closed": 8,
      "opened": 7
    },
    "2024-12-13": {
      "P1": 0,
      "P2": 32,
      "P3": 241,
      "P4": 44,
      "P5": 25,
      "Total": 342,
      "Untriaged": 0,
      "avg-time-to-close": 16809.6,
      "closed": 4,
      "opened": 6
    },
    "2024-12-20": {
      "P1": 0,
      "P2": 32,
      "P3": 232,
      "P4": 41,
      "P5": 24,
      "Total": 330,
      "Untriaged": 1,
      "avg-time-to-close": 40924.9,
      "closed": 19,
      "opened": 7
    },
    "2024-12-27": {
      "P1": 0,
      "P2": 34,
      "P3": 231,
      "P4": 41,
      "P5": 24,
      "Total": 331,
      "Untriaged": 1,
      "avg-time-to-close": 0.0,
      "closed": 0,
      "opened": 1
    },
    "2025-01-03": {
      "P1": 0,
      "P2": 34,
      "P3": 231,
      "P4": 41,
      "P5": 24,
      "Total": 334,
      "Untriaged": 4,
      "avg-time-to-close": 0.0,
      "closed": 0,
      "opened": 3
    },
    "2025-01-10": {
      "P1": 0,
      "P2": 35,
      "P3": 233,
      "P4": 41,
      "P5": 24,
      "Total": 338,
      "Untriaged": 5,
      "avg-time-to-close": 217.3,
      "closed": 4,
      "opened": 8
    },
    "2025-01-17": {
      "P1": 0,
      "P2": 37,
      "P3": 235,
      "P4": 40,
      "P5": 24,
      "Total": 336,
      "Untriaged": 0,
      "avg-time-to-close": 8113.0,
      "closed": 8,
      "opened": 6
    },
    "2025-01-24": {
      "P1": 0,
      "P2": 37,
      "P3": 234,
      "P4": 40,
      "P5": 24,
      "Total": 336,
      "Untriaged": 1,
      "avg-time-to-close": 21347.4,
      "closed": 3,
      "opened": 3
    },
    "2025-01-31": {
      "P1": 0,
      "P2": 37,
      "P3": 235,
      "P4": 40,
      "P5": 23,
      "Total": 336,
      "Untriaged": 1,
      "avg-time-to-close": 1090.2,
      "closed": 3,
      "opened": 3
    },
    "2025-02-07": {
      "P1": 1,
      "P2": 34,
      "P3": 235,
      "P4": 40,
      "P5": 23,
      "Total": 334,
      "Untriaged": 1,
      "avg-time-to-close": 319.1,
      "closed": 6,
      "opened": 4
    },
    "2025-02-14": {
      "P1": 0,
      "P2": 34,
      "P3": 237,
      "P4": 40,
      "P5": 23,
      "Total": 334,
      "Untriaged": 0,
      "avg-time-to-close": 253.3,
      "closed": 3,
      "opened": 3
    },
    "2025-02-21": {
      "P1": 0,
      "P2": 34,
      "P3": 237,
      "P4": 40,
      "P5": 23,
      "Total": 336,
      "Untriaged": 2,
      "avg-time-to-close": 0.0,
      "closed": 0,
      "opened": 2
    },
    "2025-02-28": {
      "P1": 0,
      "P2": 33,
      "P3": 237,
      "P4": 40,
      "P5": 25,
      "Total": 337,
      "Untriaged": 2,
      "avg-time-to-close": 406.7,
      "closed": 4,
      "opened": 5
    },
    "2025-03-07": {
      "P1": 0,
      "P2": 35,
      "P3": 237,
      "P4": 40,
      "P5": 25,
      "Total": 339,
      "Untriaged": 2,
      "avg-time-to-close": 1444.0,
      "closed": 1,
      "opened": 3
    }
  },
  "pontoon-prs": {
    "2024-02-09": {
      "avg-age-open": 7933.1,
      "avg-time-to-close": 1.0,
      "closed": 1,
      "open": 7,
      "opened": 1
    },
    "2024-02-16": {
      "avg-age-open": 8039.6,
      "avg-time-to-close": 104.5,
      "closed": 5,
      "open": 7,
      "opened": 5
    },
    "2024-02-23": {
      "avg-age-open": 6257.4,
      "avg-time-to-close": 1073.3,
      "closed": 7,
      "open": 8,
      "opened": 8
    },
    "2024-03-01": {
      "avg-age-open": 6374.0,
      "avg-time-to-close": 36.0,
      "closed": 8,
      "open": 8,
      "opened": 8
    },
    "2024-03-08": {
      "avg-age-open": 7421.5,
      "avg-time-to-close": 93.6,
      "closed": 3,
      "open": 7,
      "opened": 2
    },
    "2024-03-15": {
      "avg-age-open": 209.0,
      "avg-time-to-close": 3266.9,
      "closed": 16,
      "open": 4,
      "opened": 13
    },
    "2024-03-22": {
      "avg-age-open": 340.3,
      "avg-time-to-close": 114.1,
      "closed": 1,
      "open": 4,
      "opened": 1
    },
    "2024-03-29": {
      "avg-age-open": 466.0,
      "avg-time-to-close": 42.7,
      "closed": 4,
      "open": 4,
      "opened": 4
    },
    "2024-04-05": {
      "avg-age-open": 373.1,
      "avg-time-to-close": 174.6,
      "closed": 8,
      "open": 3,
      "opened": 7
    },
    "2024-04-12": {
      "avg-age-open": 362.4,
      "avg-time-to-close": 46.2,
      "closed": 5,
      "open": 4,
      "opened": 6
    },
    "2024-04-19": {
      "avg-age-open": 398.7,
      "avg-time-to-close": 210.8,
      "closed": 7,
      "open": 1,
      "opened": 5
    },
    "2024-04-26": {
      "avg-age-open": 33.8,
      "avg-time-to-close": 90.0,
      "closed": 7,
      "open": 2,
      "opened": 8
    },
    "2024-05-03": {
      "avg-age-open": 12.2,
      "avg-time-to-close": 62.7,
      "closed": 4,
      "open": 1,
      "opened": 3
    },
    "2024-05-10": {
      "avg-age-open": 17.2,
      "avg-time-to-close": 21.8,
      "closed": 5,
      "open": 1,
      "opened": 5
    },
    "2024-05-17": {
      "avg-age-open": 36.1,
      "avg-time-to-close": 14.5,
      "closed": 9,
      "open": 1,
      "opened": 9
    },
    "2024-05-24": {
      "avg-age-open": 102.9,
      "avg-time-to-close": 70.8,
      "closed": 2,
      "open": 2,
      "opened": 3
    },
    "2024-05-31": {
      "avg-age-open": 20.6,
      "avg-time-to-close": 173.9,
      "closed": 3,
      "open": 2,
      "opened": 3
    },
    "2024-06-07": {
      "avg-age-open": 104.0,
      "avg-time-to-close": 33.0,
      "closed": 4,
      "open": 2,
      "opened": 4
    },
    "2024-06-14": {
      "avg-age-open": 187.9,
      "avg-time-to-close": 23.7,
      "closed": 1,
      "open": 2,
      "opened": 1
    },
    "2024-06-21": {
      "avg-age-open": 250.6,
      "avg-time-to-close": 13.1,
      "closed": 3,
      "open": 3,
      "opened": 4
    },
    "2024-06-28": {
      "avg-age-open": 287.1,
      "avg-time-to-close": 0.0,
      "closed": 0,
      "open": 5,
      "opened": 2
    },
    "2024-07-05": {
      "avg-age-open": 438.3,
      "avg-time-to-close": 77.7,
      "closed": 6,
      "open": 4,
      "opened": 5
    },
    "2024-07-12": {
      "avg-age-open": 558.6,
      "avg-time-to-close": 63.0,
      "closed": 3,
      "open": 4,
      "opened": 3
    },
    "2024-07-19": {
      "avg-age-open": 1027.9,
      "avg-time-to-close": 371.6,
      "closed": 2,
      "open": 2,
      "opened": 0
    },
    "2024-07-26": {
      "avg-age-open": 702.8,
      "avg-time-to-close": 479.2,
      "closed": 2,
      "open": 2,
      "opened": 2
    },
    "2024-08-02": {
      "avg-age-open": 533.7,
      "avg-time-to-close": 10.6,
      "closed": 5,
      "open": 3,
      "opened": 6
    },
    "2024-08-09": {
      "avg-age-open": 534.4,
      "avg-time-to-close": 1.7,
      "closed": 1,
      "open": 4,
      "opened": 2
    },
    "2024-08-16": {
      "avg-age-open": 815.6,
      "avg-time-to-close": 172.9,
      "closed": 2,
      "open": 3,
      "opened": 1
    },
    "2024-08-23": {
      "avg-age-open": 914.5,
      "avg-time-to-close": 115.1,
      "closed": 3,
      "open": 3,
      "opened": 3
    },
    "2024-08-30": {
      "avg-age-open": 276.3,
      "avg-time-to-close": 1106.9,
      "closed": 2,
      "open": 4,
      "opened": 3
    },
    "2024-09-06": {
      "avg-age-open": 292.7,
      "avg-time-to-close": 150.6,
      "closed": 8,
      "open": 2,
      "opened": 6
    },
    "2024-09-13": {
      "avg-age-open": 245.4,
      "avg-time-to-close": 9.6,
      "closed": 14,
      "open": 4,
      "opened": 16
    },
    "2024-09-20": {
      "avg-age-open": 220.9,
      "avg-time-to-close": 32.3,
      "closed": 9,
      "open": 6,
      "opened": 10
    },
    "2024-09-27": {
      "avg-age-open": 396.9,
      "avg-time-to-close": 62.0,
      "closed": 22,
      "open": 2,
      "opened": 18
    },
    "2024-10-04": {
      "avg-age-open": 416.7,
      "avg-time-to-close": 61.2,
      "closed": 9,
      "open": 2,
      "opened": 9
    },
    "2024-10-11": {
      "avg-age-open": 323.6,
      "avg-time-to-close": 5.7,
      "closed": 5,
      "open": 4,
      "opened": 7
    },
    "2024-10-18": {
      "avg-age-open": 513.0,
      "avg-time-to-close": 32.2,
      "closed": 8,
      "open": 3,
      "opened": 7
    },
    "2024-10-25": {
      "avg-age-open": 419.3,
      "avg-time-to-close": 34.0,
      "closed": 5,
      "open": 5,
      "opened": 7
    },
    "2024-11-01": {
      "avg-age-open": 672.5,
      "avg-time-to-close": 43.4,
      "closed": 2,
      "open": 4,
      "opened": 1
    },
    "2024-11-08": {
      "avg-age-open": 979.3,
      "avg-time-to-close": 123.6,
      "closed": 3,
      "open": 3,
      "opened": 2
    },
    "2024-11-15": {
      "avg-age-open": 714.3,
      "avg-time-to-close": 6.4,
      "closed": 1,
      "open": 5,
      "opened": 3
    },
    "2024-11-22": {
      "avg-age-open": 677.7,
      "avg-time-to-close": 123.4,
      "closed": 7,
      "open": 5,
      "opened": 7
    },
    "2024-11-29": {
      "avg-age-open": 683.2,
      "avg-time-to-close": 39.3,
      "closed": 5,
      "open": 6,
      "opened": 5
    },
    "2024-12-06": {
      "avg-age-open": 1090.4,
      "avg-time-to-close": 59.0,
      "closed": 9,
      "open": 4,
      "opened": 7
    },
    "2024-12-13": {
      "avg-age-open": 1408.9,
      "avg-time-to-close": 102.5,
      "closed": 8,
      "open": 3,
      "opened": 7
    },
    "2024-12-20": {
      "avg-age-open": 978.5,
      "avg-time-to-close": 389.9,
      "closed": 7,
      "open": 2,
      "opened": 6
    },
    "2024-12-27": {
      "avg-age-open": 1146.5,
      "avg-time-to-close": 0.0,
      "closed": 0,
      "open": 2,
      "opened": 0
    },
    "2025-01-03": {
      "avg-age-open": 884.0,
      "avg-time-to-close": 0.0,
      "closed": 0,
      "open": 3,
      "opened": 1
    },
    "2025-01-10": {
      "avg-age-open": 1296.0,
      "avg-time-to-close": 105.3,
      "closed": 6,
      "open": 2,
      "opened": 5
    },
    "2025-01-17": {
      "avg-age-open": 874.6,
      "avg-time-to-close": 68.5,
      "closed": 6,
      "open": 3,
      "opened": 7
    },
    "2025-01-24": {
      "avg-age-open": 706.2,
      "avg-time-to-close": 98.2,
      "closed": 5,
      "open": 4,
      "opened": 6
    },
    "2025-01-31": {
      "avg-age-open": 793.7,
      "avg-time-to-close": 19.6,
      "closed": 4,
      "open": 4,
      "opened": 4
    },
    "2025-02-07": {
      "avg-age-open": 1168.8,
      "avg-time-to-close": 131.0,
      "closed": 3,
      "open": 3,
      "opened": 2
    },
    "2025-02-14": {
      "avg-age-open": 966.1,
      "avg-time-to-close": 31.1,
      "closed": 9,
      "open": 4,
      "opened": 10
    },
    "2025-02-21": {
      "avg-age-open": 795.2,
      "avg-time-to-close": 2.7,
      "closed": 1,
      "open": 6,
      "opened": 3
    },
    "2025-02-28": {
      "avg-age-open": 692.4,
      "avg-time-to-close": 207.5,
      "closed": 5,
      "open": 7,
      "opened": 6
    },
    "2025-03-07": {
      "avg-age-open": 797.0,
      "avg-time-to-close": 112.8,
      "closed": 5,
      "open": 7,
      "opened": 5
    }
  }
}